summator/__init__.py
summator/summator.py
summator-0.0.1.dist-info/METADATA
summator-0.0.1.dist-info/WHEEL
summator-0.0.1.dist-info/top_level.txt
summator-0.0.1.dist-info/RECORD
