Metadata-Version: 2.1
Name: summator
Version: 0.0.1
Summary: A Python toolkit for sum two numbers.
Author: Manar Yabrak
Author-email: manar.mofid@gmail.com
Classifier: Programming Language :: Python :: 3
Classifier: License :: OSI Approved :: MIT License
Classifier: Operating System :: OS Independent
Requires-Python: >=3.6
Requires-Dist: numpy (==1.21.4)
